chrdb/__init__.py
chrdb/database.py
chrdb/utils.py
pychrdb-1.2.1.dist-info/LICENSE
pychrdb-1.2.1.dist-info/METADATA
pychrdb-1.2.1.dist-info/WHEEL
pychrdb-1.2.1.dist-info/top_level.txt
pychrdb-1.2.1.dist-info/RECORD
