Metadata-Version: 2.1
Name: pychrdb
Version: 1.2.1
Summary: Improved and easy-to-use version of builtin Python's JSON
Author: das Alex
License: MIT
Project-URL: Repository, https://github.com/dasalexua/pychrdb
Keywords: chrdb,pychrdb,database,json
Requires-Python: >=3.8
License-File: LICENSE
Requires-Dist: ujson ==5.9.0
